wechat_work/__init__.py
wechat_work/__version__.py
wechat_work/wechat_work.py
wechat_work-0.0.3.dist-info/LICENSE
wechat_work-0.0.3.dist-info/METADATA
wechat_work-0.0.3.dist-info/WHEEL
wechat_work-0.0.3.dist-info/top_level.txt
wechat_work-0.0.3.dist-info/RECORD
