Metadata-Version: 2.1
Name: wechat-work
Version: 0.0.3
Summary: A tool for Wechat Work
Home-page: https://github.com/Micro-sheep/wechat_work
Author: micro sheep
Author-email: micro-sheep@outlook.com
License: MIT
Project-URL: Documentation, https://github.com/Micro-sheep/wechat_work
Project-URL: Source, https://github.com/Micro-sheep/wechat_work
Keywords: wechat,wechat work,message,notification
Platform: any
Classifier: License :: OSI Approved :: MIT License
Classifier: Programming Language :: Python :: 3.6
Classifier: Programming Language :: Python :: 3.7
Classifier: Programming Language :: Python :: 3.8
Classifier: Programming Language :: Python :: 3.9
License-File: LICENSE
Requires-Dist: requests
Requires-Dist: requests-toolbelt
